pbs_installer-2025.12.5.dist-info/METADATA
pbs_installer-2025.12.5.dist-info/WHEEL
pbs_installer-2025.12.5.dist-info/entry_points.txt
pbs_installer-2025.12.5.dist-info/licenses/LICENSE
pbs_installer/__init__.py
pbs_installer/__main__.py
pbs_installer/_install.py
pbs_installer/_utils.py
pbs_installer/_versions.py
pbs_installer/py.typed
pbs_installer-2025.12.5.dist-info/RECORD
